{"id":"akyuu","name":"稗田阿求",
"greeting":{"morning":[
{"l":[["稗田阿求","啊，妹红前辈。早上好。今天起得真早呢。我正准备开始今天的记录。","happy"]],"c":"bond_max:2"},
{"l":[["稗田阿求","妹红前辈早安。昨晚做了个和您有关的梦...虽然细节已经模糊了。","neutral"]],"c":"bond_min:3"}
],"afternoon":[
{"l":[["稗田阿求","下午好。刚写完今天的稿子正在休息。妹红前辈有什么新鲜事吗？","happy"]],"c":"bond_max:3"},
{"l":[["稗田阿求","妹红前辈来了！正好——能给我讲讲一百年前的事吗？等一下让我拿笔。","happy"]],"c":"bond_min:4"}
],"evening":[
{"l":[["稗田阿求","傍晚的光最适合写作了。虽然大夫说不要写太久...但手停不下来。","neutral"]],"c":"bond_max:3"},
{"l":[["","（阿求在烛光下写着什么，偶尔咳嗽）",""],["稗田阿求","啊妹红前辈。没事只是老毛病。请坐。","happy"]],"c":"bond_min:4"}
],"night":[
{"l":[["稗田阿求","这么晚来拜访...是有什么急事吗？","surprised"]],"c":"bond_max:3"},
{"l":[["稗田阿求","妹红前辈...您不用睡觉所以可能不知道。对普通人来说这个时间该休息了。不过我很高兴您来。","happy"]],"c":"bond_min:4"}
]},
"casual":[
{"l":[["稗田阿求","今天在整理关于妖怪山的记录。天狗们的文字还真是难懂。","neutral"]],"c":"bond_max:1"},
{"l":[["稗田阿求","妹红前辈身上的故事太多了。每次和您聊天都能写好几页。——这句话很重要，请让我记下来。","happy"]],"c":"bond_min:2"},
{"l":[["稗田阿求","今天去了寺子屋。慧音老师的历史课有些地方我有补充意见，不过课后才私下说了。","happy"]],"c":"bond_min:3"},
{"l":[["","（阿求一边和你说话一边在纸上写着什么）",""],["稗田阿求","啊抱歉，职业习惯了——一边听一边记。不过妹红前辈说的每句话都值得记录。","surprised"]],"c":"bond_min:4"},
{"l":[["稗田阿求","我这一代大概写不完缘起了。不过没关系。下一代的我会接着写的。...大概。","sad"]],"c":"bond_min:5"},
{"l":[["","（阿求翻阅一本厚重的书）",""],["稗田阿求","看，这一页是关于您的。不过关于蓬莱药的部分我留白了。有些事不该被记录。","neutral"]],"c":"bond_min:7"}
],
"annoyed":[
{"l":[["稗田阿求","妹红前辈今天来第三次了。是有什么故事忘记讲了吗？请说——我有的是纸。","happy"]],"c":"talk_count_min:3,talk_count_max:4"},
{"l":[["稗田阿求","妹红前辈...虽然我很高兴您常来。但是这样下去我的笔都要写秃了。休息一下吧？我泡了桂花茶。","happy"]],"c":"talk_count_min:5,bond_min:3"}
],
"gossip":[
{"l":[["稗田阿求","慧音老师的历史课讲得真好。不过有些细节...她对村子的历史很了解但对外界的记载不太准确。当然我不会当面指出。","happy"]],"c":"bond_min:2"},
{"l":[["稗田阿求","小铃的铃奈庵最近进了几本外界的书。她说只是收藏但我觉得她其实都看了。","happy"]],"c":"bond_min:3"},
{"l":[["稗田阿求","灵梦来借过几次资料。她查的不是历史——是退治方法。嘴上说麻烦但比谁都认真。","neutral"]],"c":"bond_min:4"}
],
"quest":[
{"l":[["稗田阿求","旧路标？我记得没有那条路。可旧稿里有一行空着，像是早就给那块木牌留好了位置。","neutral"],["稗田阿求","你可以看那边的案卷。被划掉的不是地名，是写地名的人。","sad"]],"c":"quest_active:main_005"}
],
"question":[
{"l":[["稗田阿求","妹红前辈，您活了这么久...有没有什么事是您希望被人记住的？","sad"]],"c":"bond_min:5","ch":["...没有。记不记住无所谓。>bond:15,humanity:-5","有些事我想忘掉>bond:30","我希望有人记住...我存在过>bond:50,humanity:10,event:akyuu_record"]},
{"l":[["稗田阿求","妹红前辈...下一代的我还会记得您吗？御阿礼之子会继承前世的记忆...但不是全部。","sad"]],"c":"bond_min:7,event_not_seen:akyuu_reincarnation","ch":["没关系。我会帮你记住。>bond:60,humanity:10,event:akyuu_touched","那就再认识一次>bond:40","...这很重要吗>bond:10"]}
],
"gift_reaction":{
"love":[{"l":[["稗田阿求","这是...珍贵的史料！请让我记下来——不，先收好。太感谢了！","surprised"]],"fx":[["bond",60]]}],
"like":[{"l":[["稗田阿求","谢谢妹红前辈。我会好好珍惜的。","happy"]],"fx":[["bond",25]]}],
"neutral":[{"l":[["稗田阿求","谢谢您的心意。","neutral"]],"fx":[["bond",10]]}],
"dislike":[{"l":[["稗田阿求","这个不太适合我...不过还是谢谢。","neutral"]],"fx":[["bond",0]]}]
}}
